{
  "id": "imprint",
  "name": "imprint",
  "layouts": {
    "Imprint": {
      "autoGenerated": "false",
      "description": "Cyboard Imprint",
      "layout": [
        { "label" : "=", "row": 1, "col":  0, "x":    0, "y":   1 },
        { "label" : "1", "row": 1, "col":  1, "x":    1, "y":   1 },
        { "label" : "2", "row": 1, "col":  2, "x":    2, "y":   1 },
        { "label" : "3", "row": 1, "col":  3, "x":    3, "y":   1 },
        { "label" : "4", "row": 1, "col":  4, "x":    4, "y":   1 },
        { "label" : "5", "row": 1, "col":  5, "x":    5, "y":   1 },
        { "label" : "6", "row": 1, "col":  8, "x": 11.5, "y":   1 },
        { "label" : "7", "row": 1, "col":  9, "x": 12.5, "y":   1 },
        { "label" : "8", "row": 1, "col": 10, "x": 13.5, "y":   1 },
        { "label" : "9", "row": 1, "col": 11, "x": 14.5, "y":   1 },
        { "label" : "0", "row": 1, "col": 12, "x": 15.5, "y":   1 },
        { "label" : "-", "row": 1, "col": 13, "x": 16.5, "y":   1 },

        { "label" : "Tab", "row": 2, "col":  0, "x":    0, "y":   2 },
        { "label" : "Q", "row": 2, "col":  1, "x":    1, "y":   2 },
        { "label" : "W", "row": 2, "col":  2, "x":    2, "y":   2 },
        { "label" : "E", "row": 2, "col":  3, "x":    3, "y":   2 },
        { "label" : "R", "row": 2, "col":  4, "x":    4, "y":   2 },
        { "label" : "T", "row": 2, "col":  5, "x":    5, "y":   2 },
        { "label" : "Y", "row": 2, "col":  8, "x": 11.5, "y":   2 },
        { "label" : "U", "row": 2, "col":  9, "x": 12.5, "y":   2 },
        { "label" : "I", "row": 2, "col": 10, "x": 13.5, "y":   2 },
        { "label" : "O", "row": 2, "col": 11, "x": 14.5, "y":   2 },
        { "label" : "P", "row": 2, "col": 12, "x": 15.5, "y":   2 },
        { "label" : "\\", "row": 2, "col": 13, "x": 16.5, "y":   2 },

        { "label" : "Esc", "row": 3, "col":  0, "x":    0, "y":   3 },
        { "label" : "A", "row": 3, "col":  1, "x":    1, "y":   3 },
        { "label" : "S", "row": 3, "col":  2, "x":    2, "y":   3 },
        { "label" : "D", "row": 3, "col":  3, "x":    3, "y":   3 },
        { "label" : "F", "row": 3, "col":  4, "x":    4, "y":   3 },
        { "label" : "G", "row": 3, "col":  5, "x":    5, "y":   3 },
        { "label" : "H", "row": 3, "col":  8, "x": 11.5, "y":   3 },
        { "label" : "J", "row": 3, "col":  9, "x": 12.5, "y":   3 },
        { "label" : "K", "row": 3, "col": 10, "x": 13.5, "y":   3 },
        { "label" : "L", "row": 3, "col": 11, "x": 14.5, "y":   3 },
        { "label" : ";", "row": 3, "col": 12, "x": 15.5, "y":   3 },
        { "label" : "'", "row": 3, "col": 13, "x": 16.5, "y":   3 },

        { "label" : "LShift", "row": 4, "col":  0, "x":    0, "y":   4 },
        { "label" : "Z", "row": 4, "col":  1, "x":    1, "y":   4 },
        { "label" : "X", "row": 4, "col":  2, "x":    2, "y":   4 },
        { "label" : "C", "row": 4, "col":  3, "x":    3, "y":   4 },
        { "label" : "V", "row": 4, "col":  4, "x":    4, "y":   4 },
        { "label" : "B", "row": 4, "col":  5, "x":    5, "y":   4 },
        { "label" : "N", "row": 4, "col":  8, "x": 11.5, "y":   4 },
        { "label" : "M", "row": 4, "col":  9, "x": 12.5, "y":   4 },
        { "label" : ",", "row": 4, "col": 10, "x": 13.5, "y":   4 },
        { "label" : ".", "row": 4, "col": 11, "x": 14.5, "y":   4 },
        { "label" : "/", "row": 4, "col": 12, "x": 15.5, "y":   4 },
        { "label" : "RShift", "row": 4, "col": 13, "x": 16.5, "y":   4 },

        { "label" : "Left", "row": 5, "col":  2, "x":    2, "y":   5 },
        { "label" : "Right", "row": 5, "col":  3, "x":    3, "y":   5 },
        { "label" : "Up", "row": 5, "col": 10, "x": 13.5, "y":   5 },
        { "label" : "Down", "row": 5, "col": 11, "x": 14.5, "y":   5 },

        { "label" : "LT1", "row": 6, "col":  4, "x":  5.5, "y": 5.5 },
        { "label" : "LT2", "row": 6, "col":  5, "x":  6.5, "y": 5.5 },
        { "label" : "LT3", "row": 6, "col":  6, "x":  7.5, "y": 5.5 },
        { "label" : "RT3", "row": 6, "col":  8, "x":    9, "y": 5.5 },
        { "label" : "RT2", "row": 6, "col":  9, "x":   10, "y": 5.5 },
        { "label" : "RT1", "row": 6, "col": 10, "x":   11, "y": 5.5 },

        { "label" : "LT4", "row": 7, "col":  4, "x":  5.5, "y": 6.5 },
        { "label" : "LT5", "row": 7, "col":  5, "x":  6.5, "y": 6.5 },
        { "label" : "LT6", "row": 7, "col":  6, "x":  7.5, "y": 6.5 },
        { "label" : "RT6", "row": 7, "col":  8, "x":    9, "y": 6.5 },
        { "label" : "RT5", "row": 7, "col":  9, "x":   10, "y": 6.5 },
        { "label" : "RT4", "row": 7, "col": 10, "x":   11, "y": 6.5 }
      ]
    }
  },
  "sensors": []
}
